.travis.yml
CHANGES.rst
LICENSE.txt
README.rst
bootstrap.py
buildout.cfg
setup.py
travis.cfg
alm/__init__.py
alm.solrindex.egg-info/PKG-INFO
alm.solrindex.egg-info/SOURCES.txt
alm.solrindex.egg-info/dependency_links.txt
alm.solrindex.egg-info/entry_points.txt
alm.solrindex.egg-info/namespace_packages.txt
alm.solrindex.egg-info/not-zip-safe
alm.solrindex.egg-info/requires.txt
alm.solrindex.egg-info/top_level.txt
alm/solrindex/README.rst
alm/solrindex/__init__.py
alm/solrindex/addSolrIndex.pt
alm/solrindex/browser.py
alm/solrindex/configure.zcml
alm/solrindex/exportimport.py
alm/solrindex/handlers.py
alm/solrindex/index.py
alm/solrindex/interfaces.py
alm/solrindex/profiles.zcml
alm/solrindex/quotequery.py
alm/solrindex/schema.py
alm/solrindex/solrpycore.py
alm/solrindex/utils.py
alm/solrindex/version.txt
alm/solrindex/profiles/default/catalog.xml
alm/solrindex/profiles/default/metadata.xml
alm/solrindex/profiles/uninstall/catalog.xml
alm/solrindex/scripts/__init__.py
alm/solrindex/scripts/waituri.py
alm/solrindex/tests/__init__.py
alm/solrindex/tests/schema.xml
alm/solrindex/tests/test_exportimport.py
alm/solrindex/tests/test_handlers.py
alm/solrindex/tests/test_index.py
alm/solrindex/tests/test_quotequery.py
alm/solrindex/tests/test_schema.py