Metadata-Version: 1.1
Name: alm.solrindex
Version: 1.2.0
Summary: A ZCatalog multi-index that uses Solr
